{"code": 0, "data": {"allow_search": true, "attention": false, "author_title": null, "blocked": false, "blocked_count": null, "can_del": false, "comments": [{"author_title": "", "blocked": false, "blocked_count": null, "can_del": false, "cid": 29403, "create_time": 1644312156, "is_blocked": false, "is_tmp": false, "name_id": 2, "text": "上海还有小红楼呢，这里都一样烂", "timestamp": 1644312156}, {"author_title": "", "blocked": false, "blocked_count": null, "can_del": false, "cid": 29404, "create_time": 1644312181, "is_blocked": false, "is_tmp": false, "name_id": 2, "text": "老爷心善见不到这些", "timestamp": 1644312181}, {"author_title": "", "blocked": false, "blocked_count": null, "can_del": false, "cid": 29432, "create_time": 1644317336, "is_blocked": false, "is_tmp": false, "name_id": 1, "text": "徐州？那是山东的，不是俺们江苏的", "timestamp": 1644317336}, {"author_title": "", "blocked": false, "blocked_count": null, "can_del": false, "cid": 29433, "create_time": 1644317472, "is_blocked": false, "is_tmp": true, "name_id": 3, "text": "[tmp]\nRe Alice: 支持", "timestamp": 1644317472}], "create_time": 1644308769, "cw": null, "hot_score": null, "is_blocked": false, "is_reported": null, "is_tmp": true, "last_comment_time": 1644317472, "likenum": 4, "n_attentions": 4, "n_comments": 4, "pid": 11627, "poll": null, "reply": 4, "text": "[tmp]\n#11625\n江苏徐州是什么神仙地方？据说还是“中国幸福城市”？\n[![H1cFTx.jpg](https://s4.ax1x.com/2022/02/08/H1cFTx.jpg)](https://imgtu.com/i/H1cFTx)", "timestamp": 1644308769}}