{"code": 0, "data": {"allow_search": true, "attention": false, "author_title": null, "blocked": false, "blocked_count": null, "can_del": false, "comments": [{"author_title": "", "blocked": false, "blocked_count": null, "can_del": false, "cid": 33464, "create_time": 1645504526, "is_blocked": false, "is_tmp": false, "name_id": 1, "text": "该杀", "timestamp": 1645504526}, {"author_title": "", "blocked": false, "blocked_count": null, "can_del": false, "cid": 33472, "create_time": 1645506426, "is_blocked": false, "is_tmp": false, "name_id": 0, "text": "( •̥́ ˍ •̀ू )", "timestamp": 1645506426}, {"author_title": "", "blocked": false, "blocked_count": null, "can_del": false, "cid": 33478, "create_time": 1645507344, "is_blocked": false, "is_tmp": false, "name_id": 2, "text": "网盘", "timestamp": 1645507344}, {"author_title": "", "blocked": false, "blocked_count": null, "can_del": false, "cid": 33559, "create_time": 1645520996, "is_blocked": false, "is_tmp": true, "name_id": 3, "text": "[tmp]\n你们院系没有学长学姐留下的“学习资源”吗？", "timestamp": 1645520996}, {"author_title": "", "blocked": false, "blocked_count": null, "can_del": false, "cid": 33560, "create_time": 1645521045, "is_blocked": false, "is_tmp": true, "name_id": 3, "text": "[tmp]\n或者你有认识的学长学姐吗？或者你同学室友有往年学长的学习资料吗", "timestamp": 1645521045}, {"author_title": "", "blocked": false, "blocked_count": null, "can_del": false, "cid": 33738, "create_time": 1645542934, "is_blocked": false, "is_tmp": false, "name_id": 0, "text": "和学长学姐都不熟，同学也没有，网盘是指云盘吗？怎么会有呢\n₍₍ (̨̡ ‾᷄ᗣ‾᷅ )̧̢ ₎₎", "timestamp": 1645542934}], "create_time": 1645504495, "cw": null, "hot_score": null, "is_blocked": false, "is_reported": null, "is_tmp": false, "last_comment_time": 1645542934, "likenum": 5, "n_attentions": 5, "n_comments": 6, "pid": 13362, "poll": null, "reply": 6, "text": "救命，上哪找往年学长的实验报告啊？", "timestamp": 1645504495}}