{"code": 0, "data": {"allow_search": false, "attention": false, "author_title": null, "blocked": false, "blocked_count": null, "can_del": false, "comments": null, "create_time": 1646314125, "cw": null, "hot_score": null, "is_blocked": false, "is_reported": null, "is_tmp": false, "last_comment_time": 1646333378, "likenum": 11, "n_attentions": 11, "n_comments": 17, "pid": 15370, "poll": null, "reply": 17, "text": "俄乌发展成战争自然是很不好的，我国也是一贯主张和平，并始终在呼吁双方依靠谈判来解决问题。但这几天，国内外不少人打起反战的旗号拉偏手，却是完全的别有用心。在美国人打伊拉克，叙利亚的时候，这些人不反战，还要呐喊助威，等到俄乌一冲突，他们就跳出来反战了。这些突然冒出来的“反战人士”不断渲染和西方决裂的可怕，目的不是和平，而是在吓唬任何后来者，不去挑战西方。我看这种吓唬不但不可怕，不会引起老百姓的认同，只会显示了他们的黔驴技穷。", "timestamp": 1646314125}}