{"code": 0, "data": {"allow_search": true, "attention": false, "author_title": null, "blocked": false, "blocked_count": null, "can_del": false, "comments": [{"author_title": "", "blocked": false, "blocked_count": null, "can_del": false, "cid": 50187, "create_time": 1647187795, "is_blocked": false, "is_tmp": false, "name_id": 1, "text": "这不是今天bing的图吗？", "timestamp": 1647187795}, {"author_title": "", "blocked": false, "blocked_count": null, "can_del": false, "cid": 50280, "create_time": 1647211300, "is_blocked": false, "is_tmp": false, "name_id": 2, "text": "Re Alice: 是，这bot就是爬取bing首页图片", "timestamp": 1647211300}], "create_time": 1647187201, "cw": null, "hot_score": null, "is_blocked": false, "is_reported": null, "is_tmp": false, "last_comment_time": 1647211300, "likenum": 1, "n_attentions": 1, "n_comments": 2, "pid": 18318, "poll": {"answers": [{"option": "赞", "votes": 0}, {"option": "踩", "votes": 0}, {"option": "路过", "votes": 0}], "vote": null}, "reply": 2, "text": "#报时 **北京时间 2022-03-14 00:00**\n\n>好目睫之利者，利在害中而不弃；好终身之利者，利在目睫而不为。\n>　　　　　　　　——《庄元臣》\n\n![](https://www.bing.com/th?id=OHR.SpringForward_ROW1096437918_1920x1080.jpg&rf=LaDigue_1920x1080.jpg&pid=hp)", "timestamp": 1647187201}}