{"code": 0, "data": {"allow_search": false, "attention": false, "author_title": null, "blocked": false, "blocked_count": null, "can_del": false, "comments": [{"author_title": "", "blocked": false, "blocked_count": null, "can_del": false, "cid": 55896, "create_time": 1647868774, "is_blocked": false, "is_tmp": false, "name_id": 1, "text": "插眼", "timestamp": 1647868774}, {"author_title": "", "blocked": false, "blocked_count": null, "can_del": false, "cid": 55897, "create_time": 1647869166, "is_blocked": false, "is_tmp": false, "name_id": 2, "text": "运动克服暴食", "timestamp": 1647869166}, {"author_title": "", "blocked": false, "blocked_count": null, "can_del": false, "cid": 55901, "create_time": 1647869392, "is_blocked": false, "is_tmp": false, "name_id": 3, "text": "调节心情", "timestamp": 1647869392}, {"author_title": "", "blocked": false, "blocked_count": null, "can_del": false, "cid": 55986, "create_time": 1647874884, "is_blocked": false, "is_tmp": false, "name_id": 0, "text": "Re Bob: 锻炼了反而吃更多。。", "timestamp": 1647874884}, {"author_title": "", "blocked": false, "blocked_count": null, "can_del": false, "cid": 55987, "create_time": 1647874913, "is_blocked": false, "is_tmp": false, "name_id": 0, "text": "Re Carol: 需要一些正向的自我暗示吧哈哈", "timestamp": 1647874913}, {"author_title": "", "blocked": false, "blocked_count": null, "can_del": false, "cid": 55988, "create_time": 1647874940, "is_blocked": false, "is_tmp": false, "name_id": 0, "text": "Re Carol: 我努力给自己积极的心理引导吧", "timestamp": 1647874940}], "create_time": 1647866807, "cw": null, "hot_score": null, "is_blocked": false, "is_reported": null, "is_tmp": false, "last_comment_time": 1647874940, "likenum": 3, "n_attentions": 3, "n_comments": 6, "pid": 20537, "poll": null, "reply": 6, "text": "如何克服暴食？", "timestamp": 1647866807}}