{"code": 0, "data": {"allow_search": true, "attention": false, "author_title": null, "blocked": false, "blocked_count": null, "can_del": false, "comments": [{"author_title": "", "blocked": false, "blocked_count": null, "can_del": false, "cid": 65914, "create_time": 1649051219, "is_blocked": false, "is_tmp": false, "name_id": 1, "text": "一百次？", "timestamp": 1649051219}, {"author_title": "", "blocked": false, "blocked_count": null, "can_del": false, "cid": 65928, "create_time": 1649051812, "is_blocked": false, "is_tmp": false, "name_id": 2, "text": "防疫爱好者就是没办法认清事实 用正常生活作为代价获取所谓清零的美名", "timestamp": 1649051812}, {"author_title": "", "blocked": false, "blocked_count": null, "can_del": false, "cid": 65929, "create_time": 1649051849, "is_blocked": false, "is_tmp": false, "name_id": 2, "text": "Re Alice: 我们老家三个月 有一半时间是天天核酸检测 还是二线城市", "timestamp": 1649051849}, {"author_title": "", "blocked": false, "blocked_count": null, "can_del": false, "cid": 66011, "create_time": 1649055394, "is_blocked": false, "is_tmp": false, "name_id": 3, "text": "考g去了，快走快走\n", "timestamp": 1649055394}, {"author_title": "", "blocked": false, "blocked_count": null, "can_del": false, "cid": 66910, "create_time": 1649159670, "is_blocked": false, "is_tmp": false, "name_id": 4, "text": "Re Alice: 有些岗位一天一次", "timestamp": 1649159670}, {"author_title": "", "blocked": false, "blocked_count": null, "can_del": false, "cid": 66938, "create_time": 1649162710, "is_blocked": false, "is_tmp": false, "name_id": 5, "text": "核酸检测公司真的赚麻了", "timestamp": 1649162710}, {"author_title": "", "blocked": false, "blocked_count": null, "can_del": false, "cid": 67002, "create_time": 1649166758, "is_blocked": false, "is_tmp": false, "name_id": 6, "text": "建议防疫爱好者全部判无期徒刑，隔离到死", "timestamp": 1649166758}, {"author_title": "", "blocked": false, "blocked_count": null, "can_del": false, "cid": 67336, "create_time": 1649200049, "is_blocked": false, "is_tmp": false, "name_id": 7, "text": "考公的，单位里每周一次核酸等着你捏🤗🤗🤗", "timestamp": 1649200049}, {"author_title": "", "blocked": false, "blocked_count": null, "can_del": false, "cid": 67571, "create_time": 1649222908, "is_blocked": false, "is_tmp": false, "name_id": 8, "text": "Re Francis: 你就等着感染之后大脑萎缩吧", "timestamp": 1649222908}, {"author_title": "", "blocked": false, "blocked_count": null, "can_del": false, "cid": 70902, "create_time": 1649575748, "is_blocked": false, "is_tmp": false, "name_id": 9, "text": "Re Hans: 😅清华真有人会信这种新闻？", "timestamp": 1649575748}, {"author_title": "", "blocked": false, "blocked_count": null, "can_del": false, "cid": 71691, "create_time": 1649655441, "is_blocked": false, "is_tmp": false, "name_id": 10, "text": "Re Isabella: ？？？", "timestamp": 1649655441}, {"author_title": "", "blocked": false, "blocked_count": null, "can_del": false, "cid": 71715, "create_time": 1649659249, "is_blocked": false, "is_tmp": false, "name_id": 11, "text": "Re Isabella: ？？？懂王就是你", "timestamp": 1649659249}, {"author_title": "", "blocked": false, "blocked_count": null, "can_del": false, "cid": 92889, "create_time": 1651333378, "is_blocked": false, "is_tmp": false, "name_id": 12, "text": "Re Kate: ？？？懂王就是你", "timestamp": 1651333378}, {"author_title": "", "blocked": false, "blocked_count": null, "can_del": false, "cid": 93699, "create_time": 1651391396, "is_blocked": false, "is_tmp": false, "name_id": 13, "text": "Re Grace: 父母都体制内，并没有每周一次。nvpy在部委，和大领导比较近，倒是每周一次", "timestamp": 1651391396}, {"author_title": "", "blocked": false, "blocked_count": null, "can_del": false, "cid": 109300, "create_time": 1652247561, "is_blocked": false, "is_tmp": false, "name_id": 14, "text": "Re Hans: 大脑萎缩多正常，精神状态不好也会大脑萎缩", "timestamp": 1652247561}], "create_time": 1649048291, "cw": null, "hot_score": null, "is_blocked": false, "is_reported": null, "is_tmp": false, "last_comment_time": 1652247561, "likenum": 13, "n_attentions": 13, "n_comments": 15, "pid": 24340, "poll": null, "reply": 15, "text": "防疫爱好者以为的动态清零：\n少数几个城市封很短一段时间，就能换来大多数人的正常生活。\n>\n实际上，Omicron BA.2 下的动态清零可能是这样的：大多数人都可以享受到瑞丽的待遇，每个城市每年都要封几个月，14亿人每人每年做一百次核酸检测。", "timestamp": 1649048291}}