{"code": 0, "data": {"allow_search": true, "attention": false, "author_title": "树洞公告", "blocked": false, "blocked_count": null, "can_del": false, "comments": null, "create_time": 1649147425, "cw": null, "hot_score": null, "is_blocked": false, "is_reported": null, "is_tmp": false, "last_comment_time": 1649156688, "likenum": 5, "n_attentions": 5, "n_comments": 5, "pid": 24701, "poll": {"answers": [{"option": "低了", "votes": 18}, {"option": "合适", "votes": 15}, {"option": "高了", "votes": 2}], "vote": null}, "reply": 5, "text": "你认为十次拉黑自动被所有人拉黑的阈值", "timestamp": 1649147425}}