{"code": 0, "data": {"allow_search": false, "attention": false, "author_title": null, "blocked": false, "blocked_count": null, "can_del": false, "comments": [{"author_title": "", "blocked": false, "blocked_count": null, "can_del": false, "cid": 85087, "create_time": 1650729642, "is_blocked": false, "is_tmp": false, "name_id": 1, "text": "好家伙 没准桃花能加速科研", "timestamp": 1650729642}, {"author_title": "", "blocked": false, "blocked_count": null, "can_del": false, "cid": 85088, "create_time": 1650729649, "is_blocked": false, "is_tmp": false, "name_id": 2, "text": "？", "timestamp": 1650729649}, {"author_title": "", "blocked": false, "blocked_count": null, "can_del": false, "cid": 85089, "create_time": 1650729675, "is_blocked": false, "is_tmp": false, "name_id": 1, "text": "跟桃花说 你要是能帮我出sci我就答应你（bushi", "timestamp": 1650729675}], "create_time": 1650729584, "cw": null, "hot_score": null, "is_blocked": false, "is_reported": null, "is_tmp": false, "last_comment_time": 1650729675, "likenum": 3, "n_attentions": 3, "n_comments": 3, "pid": 31007, "poll": null, "reply": 3, "text": "我想要自己科研成功一点啊。然鹅，我科研并不成功......各种失败 挫败 挫败.......桃花运倒是不错......呃！但是我现在根本无心恋爱 只想科研！！！不好意思，就是不想嫁人啊……可以拿这桃花运换科研成功吗", "timestamp": 1650729584}}