{"code": 0, "data": {"allow_search": false, "attention": false, "author_title": null, "blocked": false, "blocked_count": null, "can_del": false, "comments": [{"author_title": "", "blocked": false, "blocked_count": null, "can_del": false, "cid": 127397, "create_time": 1653012935, "is_blocked": false, "is_tmp": false, "name_id": 1, "text": "看怎么说了。打赢了大上海保卫战，这是有功啊", "timestamp": 1653012935}, {"author_title": "", "blocked": false, "blocked_count": null, "can_del": false, "cid": 127429, "create_time": 1653013822, "is_blocked": false, "is_tmp": false, "name_id": 2, "text": "肯定入常", "timestamp": 1653013822}, {"author_title": "", "blocked": false, "blocked_count": null, "can_del": false, "cid": 127442, "create_time": 1653014758, "is_blocked": false, "is_tmp": false, "name_id": 3, "text": "肯定入厂", "timestamp": 1653014758}], "create_time": 1653012716, "cw": "政治相关", "hot_score": null, "is_blocked": false, "is_reported": null, "is_tmp": false, "last_comment_time": 1653014758, "likenum": 3, "n_attentions": 3, "n_comments": 3, "pid": 44713, "poll": {"answers": [{"option": "可能入常", "votes": 19}, {"option": "不可能入常", "votes": 25}, {"option": "瓜", "votes": 38}], "vote": null}, "reply": 3, "text": "李强把上海搞成这样，二十大还可能入常吗", "timestamp": 1653012716}}