{"code": 0, "data": {"allow_search": false, "attention": false, "author_title": null, "blocked": false, "blocked_count": null, "can_del": false, "comments": [{"author_title": "", "blocked": false, "blocked_count": null, "can_del": false, "cid": 127557, "create_time": 1653018808, "is_blocked": false, "is_tmp": false, "name_id": 1, "text": "为啥", "timestamp": 1653018808}, {"author_title": "", "blocked": false, "blocked_count": null, "can_del": false, "cid": 127563, "create_time": 1653018909, "is_blocked": false, "is_tmp": false, "name_id": 0, "text": "Re Alice: 充满了算计和对另一半的阴暗揣测看着感觉很不适", "timestamp": 1653018909}, {"author_title": "", "blocked": false, "blocked_count": null, "can_del": false, "cid": 127564, "create_time": 1653018951, "is_blocked": false, "is_tmp": false, "name_id": 0, "text": "得了看到“男”“女”高频出现的内容就头晕的病", "timestamp": 1653018951}, {"author_title": "", "blocked": false, "blocked_count": null, "can_del": false, "cid": 127575, "create_time": 1653019291, "is_blocked": false, "is_tmp": false, "name_id": 1, "text": "那就看看这个#44699", "timestamp": 1653019291}, {"author_title": "", "blocked": false, "blocked_count": null, "can_del": false, "cid": 127592, "create_time": 1653019650, "is_blocked": false, "is_tmp": false, "name_id": 0, "text": "Re Alice: 虽然单身鼠鼠dz并不是很想看小情侣秀恩爱，但是宁可树洞都是这种内容，，", "timestamp": 1653019650}, {"author_title": "", "blocked": false, "blocked_count": null, "can_del": false, "cid": 127593, "create_time": 1653019711, "is_blocked": false, "is_tmp": false, "name_id": 0, "text": "dz决定打开老友记看Chandler和Monica", "timestamp": 1653019711}], "create_time": 1653018789, "cw": null, "hot_score": null, "is_blocked": false, "is_reported": null, "is_tmp": false, "last_comment_time": 1653019711, "likenum": 2, "n_attentions": 2, "n_comments": 6, "pid": 44756, "poll": null, "reply": 6, "text": "你们还是键政吧，别聊感情和婚姻了。。。", "timestamp": 1653018789}}