{"code": 0, "data": {"allow_search": true, "attention": false, "author_title": null, "blocked": false, "blocked_count": null, "can_del": false, "comments": [{"author_title": "", "blocked": false, "blocked_count": null, "can_del": false, "cid": 165432, "create_time": 1653819921, "is_blocked": false, "is_tmp": false, "name_id": 1, "text": "谢谢老师", "timestamp": 1653819921}, {"author_title": "", "blocked": false, "blocked_count": null, "can_del": false, "cid": 165435, "create_time": 1653820060, "is_blocked": false, "is_tmp": false, "name_id": 2, "text": "道理我都懂，但是二十几岁的阶段已经过了一多半还是没有性经历，还是挺遗憾的", "timestamp": 1653820060}, {"author_title": "", "blocked": false, "blocked_count": null, "can_del": false, "cid": 165436, "create_time": 1653820158, "is_blocked": false, "is_tmp": false, "name_id": 0, "text": "Re Alice: 西芹啊，欠的奖金啥时候发？", "timestamp": 1653820158}, {"author_title": "", "blocked": false, "blocked_count": null, "can_del": false, "cid": 165438, "create_time": 1653820241, "is_blocked": false, "is_tmp": false, "name_id": 3, "text": "xs，本人不y且不喜欢y，但是你这个评价我看着确实难受。如果你不能理解一个行为，至少请你尊重他，而不是去弱化这个行为的意义。\n你从公序良俗上去攻击这种行为在我看来都要舒服很多。\n有的人就是喜欢看着云发呆，你偏要来跟我说发呆眼睛好这件事离开了眺望远方之外毫无意义。然后跟我说抬起头向前走，想清楚自己想要什么？\n如果你来下水道，请你接受下水道自有自己的舞台和自己的明星。", "timestamp": 1653820241}, {"author_title": "", "blocked": false, "blocked_count": null, "can_del": false, "cid": 165441, "create_time": 1653820396, "is_blocked": false, "is_tmp": false, "name_id": 4, "text": "说实话 我感觉没人意气风发捏\n以及正常人应该都不会被带偏", "timestamp": 1653820396}, {"author_title": "", "blocked": false, "blocked_count": null, "can_del": false, "cid": 165442, "create_time": 1653820444, "is_blocked": false, "is_tmp": false, "name_id": 4, "text": "Re Carol: 说得好", "timestamp": 1653820444}, {"author_title": "", "blocked": false, "blocked_count": null, "can_del": false, "cid": 165443, "create_time": 1653820476, "is_blocked": false, "is_tmp": false, "name_id": 0, "text": "Re Carol: 有的人喜欢约那就约呗，我也妹说约不好啊。这跟我劝可爱的🐭🐭们不要妄自菲薄、不要把跟陌生人交配看得太高有啥矛盾的？", "timestamp": 1653820476}, {"author_title": "", "blocked": false, "blocked_count": null, "can_del": false, "cid": 165447, "create_time": 1653820594, "is_blocked": false, "is_tmp": false, "name_id": 5, "text": "虽然不约炮只吃瓜，但是我是要😅\n别人哪里意气风发了，我又哪里自卑了，我只不过吃个和紫操学姐一样大瓜罢了", "timestamp": 1653820594}, {"author_title": "", "blocked": false, "blocked_count": null, "can_del": false, "cid": 165451, "create_time": 1653820688, "is_blocked": false, "is_tmp": false, "name_id": 5, "text": "大多数人自卑的最多也就是自身硬件条件罢了，就像我没有180，仅此而已", "timestamp": 1653820688}, {"author_title": "", "blocked": false, "blocked_count": null, "can_del": false, "cid": 165452, "create_time": 1653820726, "is_blocked": false, "is_tmp": false, "name_id": 4, "text": "Re Dave: “会不会因此”的argument看着挺搞笑的。其实就是管太多，又不承认是管太多，非要找个justification罢了。", "timestamp": 1653820726}, {"author_title": "", "blocked": false, "blocked_count": null, "can_del": false, "cid": 165453, "create_time": 1653820737, "is_blocked": false, "is_tmp": false, "name_id": 0, "text": "Re Eve: 没自卑那是好事捏🤗", "timestamp": 1653820737}, {"author_title": "", "blocked": false, "blocked_count": null, "can_del": false, "cid": 165454, "create_time": 1653820739, "is_blocked": false, "is_tmp": false, "name_id": 3, "text": "Re 洞主: 确实。不过我觉得鼠鼠们也就是嘴上一说，也不会真的有人因为逛sd逛多了觉得自己y不到而有挫败hhh", "timestamp": 1653820739}, {"author_title": "", "blocked": false, "blocked_count": null, "can_del": false, "cid": 165469, "create_time": 1653821120, "is_blocked": false, "is_tmp": false, "name_id": 6, "text": "说得好", "timestamp": 1653821120}, {"author_title": "", "blocked": false, "blocked_count": null, "can_del": false, "cid": 165481, "create_time": 1653821438, "is_blocked": false, "is_tmp": false, "name_id": 0, "text": "Re Carol: \n> 也不会真的有人因为逛sd逛多了觉得自己y不到而有挫败hhh\n\n这个我觉得不好说耶", "timestamp": 1653821438}, {"author_title": "", "blocked": false, "blocked_count": null, "can_del": false, "cid": 165553, "create_time": 1653822339, "is_blocked": false, "is_tmp": false, "name_id": 7, "text": "但是真的想要恋爱啊😭想要可以分享一切的朋友😭😭😭", "timestamp": 1653822339}, {"author_title": "", "blocked": false, "blocked_count": null, "can_del": false, "cid": 165556, "create_time": 1653822398, "is_blocked": false, "is_tmp": false, "name_id": 7, "text": "伴侣和事业都和🐭🐭无关", "timestamp": 1653822398}, {"author_title": "", "blocked": false, "blocked_count": null, "can_del": false, "cid": 165608, "create_time": 1653823460, "is_blocked": false, "is_tmp": false, "name_id": 8, "text": "管好你自己~", "timestamp": 1653823460}], "create_time": 1653819738, "cw": null, "hot_score": null, "is_blocked": false, "is_reported": null, "is_tmp": false, "last_comment_time": 1653823460, "likenum": 13, "n_attentions": 13, "n_comments": 17, "pid": 53884, "poll": null, "reply": 17, "text": "#53258\n\n接受评论区说我缺了点同情的批评。\n\n那条洞是昨天深夜发的，当时的氛围是怎样的呢？一帮约炮达人在意气风发，一帮所谓的鼠鼠在妄自菲薄和羡慕不已。网络空间与现实世界的反差让我有一种荒谬感，下水道见不得光的老鼠成了舞台上的大明星，大街上的普通人成了没脸见人的老鼠。因为自己曾经的经历，又不禁思考这样的氛围会对树洞用户，尤其刚刚进入大学不满一年的小朋友带来怎样的影响。会不会因此把能不能约炮当成衡量人生是否成功的重要标准？会不会因此把正常谈恋爱当成解锁性经验方便以后约炮的工具？\n\n因为这些原因，写下那段文字的时候确实多了几分恶毒，少了几分温情。\n\n当然了，看到某个约炮人在评论区破防了大喊“羡慕嫉妒恨吧 条件就是比你好”的样子还是有点意思。但更多还是希望与各位鼠鼠们共勉：适当抬头看看现实世界吧。身高、生殖器尺寸这些先天的东西，离开了约炮这个语境，根本没那么重要——或许在工地上或者流水线工厂里还重要一点，在华子这些东西的重要性又被进一步削弱了。约炮也不过是填补自己空虚人生的一种娱乐方式罢了，并不比你宅在寝室里打游戏或者去爬山去拔河更高级。我对约炮不想做什么道德上的批判，然而见不得光就是见不得光。交配带来的多巴胺也不一定比得上游戏、运动、竞技等等。\n\n不要被匿名平台上的约炮人带偏了，抬起头，向前走，想清楚自己到底想要什么，过好自己的充实人生。\n", "timestamp": 1653819738}}