{"code": 0, "data": {"allow_search": true, "attention": false, "author_title": null, "blocked": false, "blocked_count": null, "can_del": false, "comments": [{"author_title": "", "blocked": false, "blocked_count": null, "can_del": false, "cid": 197588, "create_time": 1654757747, "is_blocked": false, "is_tmp": false, "name_id": 1, "text": "谈过几个", "timestamp": 1654757747}], "create_time": 1654756893, "cw": null, "hot_score": null, "is_blocked": false, "is_reported": null, "is_tmp": true, "last_comment_time": 1654757747, "likenum": 1, "n_attentions": 1, "n_comments": 1, "pid": 61487, "poll": null, "reply": 1, "text": "这世上真的有长久的爱情吗。dz对这个好悲观。前几任都是dz觉得不喜欢对方于是分手了…自己渣了别人的感觉也好难受…每一任都好像情深不寿的样子，根本无法理解dz为什么会变得不喜欢他们…但是喜欢，哪怕是爱，真的能那么长久吗。dz之前就说希望下一个宁愿自己被渣也不想渣别人了…现任好像又…情深不寿的样子，甚至感到害怕了。害怕最后又是自己渣了他。可是哪里会有人确定的一定就不会分开呢…npy说着就是感觉不能接受离开我…说实在的到最后真的都能接受的吧，dz甚至悲观到觉得npy现在这样说，一年之后还不一定谁先不喜欢谁呢…dz真的太渣了…这样还是不谈恋爱为妙吧。\n", "timestamp": 1654756893}}