{"code": 0, "data": {"allow_search": false, "attention": false, "author_title": null, "blocked": false, "blocked_count": null, "can_del": false, "comments": [{"author_title": "", "blocked": false, "blocked_count": null, "can_del": false, "cid": 227191, "create_time": 1655454380, "is_blocked": false, "is_tmp": false, "name_id": 1, "text": "cy\n", "timestamp": 1655454380}, {"author_title": "", "blocked": false, "blocked_count": null, "can_del": false, "cid": 227266, "create_time": 1655455483, "is_blocked": false, "is_tmp": false, "name_id": 2, "text": "cy", "timestamp": 1655455483}], "create_time": 1655453203, "cw": null, "hot_score": null, "is_blocked": false, "is_reported": null, "is_tmp": false, "last_comment_time": 1655455483, "likenum": 3, "n_attentions": 3, "n_comments": 2, "pid": 67157, "poll": null, "reply": 2, "text": "交换生项目有哪些啊，我在info上搜不到呢，雅思有些什么要求啊", "timestamp": 1655453203}}