{"code": 0, "data": {"allow_search": true, "attention": false, "author_title": null, "blocked": false, "blocked_count": null, "can_del": false, "comments": [{"author_title": "", "blocked": false, "blocked_count": null, "can_del": false, "cid": 246142, "create_time": 1655907669, "is_blocked": false, "is_tmp": false, "name_id": 1, "text": "不同的人长的不一样 很正常", "timestamp": 1655907669}, {"author_title": "", "blocked": false, "blocked_count": null, "can_del": false, "cid": 246160, "create_time": 1655907905, "is_blocked": false, "is_tmp": false, "name_id": 2, "text": "个体差异，我的就是立起来贴肚皮，在里面会顶阴道壁而且刺激比较大，羡慕你们平的。", "timestamp": 1655907905}, {"author_title": "", "blocked": false, "blocked_count": null, "can_del": false, "cid": 246163, "create_time": 1655907983, "is_blocked": false, "is_tmp": false, "name_id": 3, "text": "我也直贴肚皮，掰下去会弹起来", "timestamp": 1655907983}, {"author_title": "", "blocked": false, "blocked_count": null, "can_del": false, "cid": 246178, "create_time": 1655908355, "is_blocked": false, "is_tmp": false, "name_id": 0, "text": "Re Bob: 感觉能贴上去的更优秀啊！", "timestamp": 1655908355}, {"author_title": "", "blocked": false, "blocked_count": null, "can_del": false, "cid": 246180, "create_time": 1655908409, "is_blocked": false, "is_tmp": false, "name_id": 0, "text": "555为什么大家都能贴肚皮，羡慕哭了，我摁在肚皮上就直接回弹了", "timestamp": 1655908409}], "create_time": 1655907554, "cw": "xxg", "hot_score": null, "is_blocked": false, "is_reported": null, "is_tmp": false, "last_comment_time": 1655908409, "likenum": 3, "n_attentions": 3, "n_comments": 5, "pid": 70733, "poll": null, "reply": 5, "text": "好奇，不同男生boqi的状态是不是不一样啊？dz自己硬的时候就是和身体大概呈90°，直直的那种，往腹部掰一下也会复位。但是看到小片片里面有硬起来直接贴肚皮的，还有的弧度特别明显，为啥我就不行，dz这个算不算羊尾啊。。。。", "timestamp": 1655907554}}