{"code": 0, "data": {"allow_search": true, "attention": false, "author_title": null, "blocked": false, "blocked_count": null, "can_del": false, "comments": [{"author_title": "", "blocked": false, "blocked_count": null, "can_del": false, "cid": 259315, "create_time": 1656315920, "is_blocked": false, "is_tmp": false, "name_id": 1, "text": "wsl不香吗", "timestamp": 1656315920}, {"author_title": "", "blocked": false, "blocked_count": null, "can_del": false, "cid": 259316, "create_time": 1656315961, "is_blocked": false, "is_tmp": false, "name_id": 2, "text": "按教程就好", "timestamp": 1656315961}, {"author_title": "", "blocked": false, "blocked_count": null, "can_del": false, "cid": 259317, "create_time": 1656316045, "is_blocked": false, "is_tmp": false, "name_id": 0, "text": "Re Alice: emmm我手头俩电脑，想一个用WSL，另一个搞成双系统", "timestamp": 1656316045}, {"author_title": "", "blocked": false, "blocked_count": null, "can_del": false, "cid": 259328, "create_time": 1656316381, "is_blocked": false, "is_tmp": false, "name_id": 3, "text": "csdn上就有教程很详细", "timestamp": 1656316381}, {"author_title": "", "blocked": false, "blocked_count": null, "can_del": false, "cid": 259329, "create_time": 1656316467, "is_blocked": false, "is_tmp": false, "name_id": 4, "text": "显卡是个大问题，但愿你不是双显卡笔记本", "timestamp": 1656316467}, {"author_title": "", "blocked": false, "blocked_count": null, "can_del": false, "cid": 259334, "create_time": 1656316544, "is_blocked": false, "is_tmp": false, "name_id": 5, "text": "听我一句劝，别搞双系统，既然你有俩电脑，一个win一个linux不香吗", "timestamp": 1656316544}, {"author_title": "", "blocked": false, "blocked_count": null, "can_del": false, "cid": 259336, "create_time": 1656316586, "is_blocked": false, "is_tmp": false, "name_id": 4, "text": "而且每个发行版方法也有不同，Ubuntu这种可以纯图形界面操作，arch这种就要看wiki了。", "timestamp": 1656316586}, {"author_title": "", "blocked": false, "blocked_count": null, "can_del": false, "cid": 259351, "create_time": 1656316857, "is_blocked": false, "is_tmp": false, "name_id": 4, "text": "双系统有双系统的好处，我之前就是长期三系统（折腾黑苹果），好处是折腾起来很快乐，坏处是引导经常崩，万一碰上急事直接寄。", "timestamp": 1656316857}, {"author_title": "", "blocked": false, "blocked_count": null, "can_del": false, "cid": 259374, "create_time": 1656317778, "is_blocked": false, "is_tmp": false, "name_id": 6, "text": "以前搞过。主要的问题，一个是要自己设置挂载，一个是可能的时间冲突，似乎需要调Linux。", "timestamp": 1656317778}, {"author_title": "", "blocked": false, "blocked_count": null, "can_del": false, "cid": 259377, "create_time": 1656317813, "is_blocked": false, "is_tmp": false, "name_id": 6, "text": "当时还是Windows 8.1和Ubuntu搭配的。记得还出了快速启动的问题，上一次使用windows关机后会自动从快速启动进Linux", "timestamp": 1656317813}, {"author_title": "", "blocked": false, "blocked_count": null, "can_del": false, "cid": 259433, "create_time": 1656319237, "is_blocked": false, "is_tmp": false, "name_id": 4, "text": "Re Francis: 时间冲突可以改win的主板时间读取方式，因为一个是主板时间+时区偏移，一个是直接显示主板时间。快速启动双系统bug特别多，我当时就出过硬件缓存的问题，后来就把快速启动关了。", "timestamp": 1656319237}], "create_time": 1656315752, "cw": null, "hot_score": null, "is_blocked": false, "is_reported": null, "is_tmp": false, "last_comment_time": 1656319237, "likenum": 9, "n_attentions": 9, "n_comments": 11, "pid": 73686, "poll": null, "reply": 11, "text": "CS专业小白问各位个问题，想装Linux双系统有什么比较可靠的教程么？手里有闲置U盘。。以前一直用WSL现在想试试双系统", "timestamp": 1656315752}}