{"code": 0, "data": {"allow_search": true, "attention": false, "author_title": null, "blocked": false, "blocked_count": null, "can_del": false, "comments": [{"author_title": "", "blocked": false, "blocked_count": null, "can_del": false, "cid": 267292, "create_time": 1656600779, "is_blocked": false, "is_tmp": false, "name_id": 1, "text": "身上不痒，头不油吗", "timestamp": 1656600779}, {"author_title": "", "blocked": false, "blocked_count": null, "can_del": false, "cid": 267301, "create_time": 1656600930, "is_blocked": false, "is_tmp": false, "name_id": 2, "text": "家长不催吗", "timestamp": 1656600930}, {"author_title": "", "blocked": false, "blocked_count": null, "can_del": false, "cid": 267305, "create_time": 1656601003, "is_blocked": false, "is_tmp": false, "name_id": 0, "text": "Re Alice: 洗头不洗澡，身体不痒", "timestamp": 1656601003}], "create_time": 1656600661, "cw": null, "hot_score": null, "is_blocked": false, "is_reported": null, "is_tmp": false, "last_comment_time": 1656601003, "likenum": 3, "n_attentions": 3, "n_comments": 3, "pid": 75722, "poll": null, "reply": 3, "text": "回家以后一周都不洗一次澡，每次想洗澡都哎过一会再洗，拖着拖着就晚上，然后就第二天再洗\n学习也是一样一直拖着", "timestamp": 1656600661}}