{"code": 0, "data": {"allow_search": false, "attention": false, "author_title": null, "blocked": false, "blocked_count": null, "can_del": false, "comments": [], "create_time": 1657283142, "cw": "令人不适", "hot_score": null, "is_blocked": false, "is_reported": null, "is_tmp": false, "last_comment_time": 1657283142, "likenum": 1, "n_attentions": 1, "n_comments": 0, "pid": 79868, "poll": null, "reply": 0, "text": "\n![](https://bafkreicwuxfbxalgyzimvdxnqazuzc7ezsmv4ysczzunolpnotk32vux4m.ipfs.dweb.link/?filename=mmexport1657283091382.jpg&filetype=image%2Fjpeg) [加载失败请点击此](https://hole-thu.github.io/ipfs.html#bafkreicwuxfbxalgyzimvdxnqazuzc7ezsmv4ysczzunolpnotk32vux4m)\n\n---\n毛君，asshole!", "timestamp": 1657283142}}