{"code": 0, "data": {"allow_search": true, "attention": false, "author_title": null, "blocked": false, "blocked_count": null, "can_del": false, "comments": [{"author_title": "", "blocked": false, "blocked_count": null, "can_del": false, "cid": 282706, "create_time": 1657287730, "is_blocked": false, "is_tmp": false, "name_id": 1, "text": "这不就有了吗", "timestamp": 1657287730}, {"author_title": "", "blocked": false, "blocked_count": null, "can_del": false, "cid": 282852, "create_time": 1657289759, "is_blocked": false, "is_tmp": false, "name_id": 2, "text": "留号就有了", "timestamp": 1657289759}], "create_time": 1657287614, "cw": null, "hot_score": null, "is_blocked": false, "is_reported": null, "is_tmp": false, "last_comment_time": 1657289759, "likenum": 4, "n_attentions": 4, "n_comments": 2, "pid": 79939, "poll": null, "reply": 2, "text": "我以为我有男朋友\n但是我没有", "timestamp": 1657287614}}