{"code": 0, "data": {"allow_search": true, "attention": false, "author_title": null, "blocked": false, "blocked_count": null, "can_del": false, "comments": [{"author_title": "", "blocked": false, "blocked_count": null, "can_del": false, "cid": 295661, "create_time": 1657866465, "is_blocked": false, "is_tmp": false, "name_id": 1, "text": "都ex了 何必呢", "timestamp": 1657866465}, {"author_title": "", "blocked": false, "blocked_count": null, "can_del": false, "cid": 295664, "create_time": 1657866503, "is_blocked": false, "is_tmp": false, "name_id": 1, "text": "过去就让他过去吧", "timestamp": 1657866503}, {"author_title": "", "blocked": false, "blocked_count": null, "can_del": false, "cid": 296275, "create_time": 1657892279, "is_blocked": false, "is_tmp": false, "name_id": 2, "text": "想知道就直接问就行了，别有那么多想法", "timestamp": 1657892279}], "create_time": 1657866108, "cw": null, "hot_score": null, "is_blocked": false, "is_reported": null, "is_tmp": false, "last_comment_time": 1657892279, "likenum": 3, "n_attentions": 3, "n_comments": 3, "pid": 83467, "poll": null, "reply": 3, "text": "如何不动声色地知道ex是否单身？\n只知道ta朋友圈没有官宣", "timestamp": 1657866108}}