{"code": 0, "data": {"allow_search": false, "attention": false, "author_title": null, "blocked": false, "blocked_count": null, "can_del": false, "comments": [{"author_title": "", "blocked": false, "blocked_count": null, "can_del": false, "cid": 296792, "create_time": 1657935759, "is_blocked": false, "is_tmp": false, "name_id": 1, "text": "?", "timestamp": 1657935759}, {"author_title": "", "blocked": false, "blocked_count": null, "can_del": false, "cid": 296796, "create_time": 1657936101, "is_blocked": false, "is_tmp": false, "name_id": 2, "text": "什么夏令营", "timestamp": 1657936101}, {"author_title": "", "blocked": false, "blocked_count": null, "can_del": false, "cid": 296856, "create_time": 1657938989, "is_blocked": false, "is_tmp": false, "name_id": 0, "text": "Re Bob: 7.4开始的那个", "timestamp": 1657938989}, {"author_title": "", "blocked": false, "blocked_count": null, "can_del": false, "cid": 297383, "create_time": 1657961713, "is_blocked": false, "is_tmp": false, "name_id": 3, "text": "曾经是领军计划免笔试（暴露年龄的回答", "timestamp": 1657961713}, {"author_title": "", "blocked": false, "blocked_count": null, "can_del": false, "cid": 297388, "create_time": 1657961776, "is_blocked": false, "is_tmp": false, "name_id": 4, "text": "强基优秀良好评定应该是", "timestamp": 1657961776}, {"author_title": "", "blocked": false, "blocked_count": null, "can_del": false, "cid": 297452, "create_time": 1657965171, "is_blocked": false, "is_tmp": false, "name_id": 5, "text": "？？我指的是本科生报的，可能和保研有关系的那个夏令营orz", "timestamp": 1657965171}], "create_time": 1657932467, "cw": null, "hot_score": null, "is_blocked": false, "is_reported": null, "is_tmp": false, "last_comment_time": 1657965171, "likenum": 6, "n_attentions": 6, "n_comments": 6, "pid": 83814, "poll": null, "reply": 6, "text": "清华夏令营的优秀营员是有什么作用啊？", "timestamp": 1657932467}}