{"code": 0, "data": {"allow_search": true, "attention": false, "author_title": null, "blocked": false, "blocked_count": null, "can_del": false, "comments": [{"author_title": "", "blocked": false, "blocked_count": null, "can_del": false, "cid": 318303, "create_time": 1659077955, "is_blocked": false, "is_tmp": false, "name_id": 0, "text": "为啥这都能被举报", "timestamp": 1659077955}, {"author_title": "", "blocked": false, "blocked_count": null, "can_del": false, "cid": 318304, "create_time": 1659077966, "is_blocked": false, "is_tmp": false, "name_id": 0, "text": "12分钟之前 7-29 14:47:49   Report A9...19\n#90246\n评论区Francis，评论id 318184", "timestamp": 1659077966}, {"author_title": "", "blocked": false, "blocked_count": null, "can_del": false, "cid": 318350, "create_time": 1659080797, "is_blocked": false, "is_tmp": false, "name_id": 1, "text": "Re 洞主: xs了 这不就是洞主自己发的吗，举报评论干嘛？？？", "timestamp": 1659080797}], "create_time": 1659077942, "cw": null, "hot_score": null, "is_blocked": false, "is_reported": null, "is_tmp": false, "last_comment_time": 1659080797, "likenum": 2, "n_attentions": 2, "n_comments": 3, "pid": 90322, "poll": null, "reply": 3, "text": "#90246  \n好像这个缺失了很多树洞啊", "timestamp": 1659077942}}