{"code": 0, "data": {"allow_search": true, "attention": false, "author_title": null, "blocked": false, "blocked_count": null, "can_del": false, "comments": [{"author_title": "", "blocked": false, "blocked_count": null, "can_del": false, "cid": 320644, "create_time": 1659195230, "is_blocked": false, "is_tmp": false, "name_id": 0, "text": "他们总是在忙他们自己的事，有谁会关心一个在城市里乱逛的人的想法呢？", "timestamp": 1659195230}, {"author_title": "", "blocked": false, "blocked_count": null, "can_del": false, "cid": 320649, "create_time": 1659195419, "is_blocked": false, "is_tmp": false, "name_id": 1, "text": "在哪个城市乱逛呢 可能分享到树洞会好一些", "timestamp": 1659195419}, {"author_title": "", "blocked": false, "blocked_count": null, "can_del": false, "cid": 320680, "create_time": 1659196378, "is_blocked": false, "is_tmp": false, "name_id": 0, "text": "Re Alice: 上海", "timestamp": 1659196378}, {"author_title": "", "blocked": false, "blocked_count": null, "can_del": false, "cid": 320684, "create_time": 1659196538, "is_blocked": false, "is_tmp": false, "name_id": 0, "text": "Re Alice: 你说的对，在树洞我可以同时是实习的a，吃饭的b，骑车的c，看海的d，拍照的e，看番的f，读书的g，看展的h。", "timestamp": 1659196538}, {"author_title": "", "blocked": false, "blocked_count": null, "can_del": false, "cid": 320689, "create_time": 1659196666, "is_blocked": false, "is_tmp": false, "name_id": 0, "text": "树洞还是好", "timestamp": 1659196666}], "create_time": 1659195079, "cw": null, "hot_score": null, "is_blocked": false, "is_reported": null, "is_tmp": false, "last_comment_time": 1659196666, "likenum": 2, "n_attentions": 2, "n_comments": 5, "pid": 90980, "poll": null, "reply": 5, "text": "我有这么多想要分享的，却只能随机地投到一些群里，而且一般得不到回应。没人理我。如果想有人理的话又要花时间建立人际关系，而且也不一定成功，好难。", "timestamp": 1659195079}}