{"code": 0, "data": {"allow_search": true, "attention": false, "author_title": null, "blocked": false, "blocked_count": null, "can_del": false, "comments": [{"author_title": "", "blocked": false, "blocked_count": null, "can_del": false, "cid": 322033, "create_time": 1659283402, "is_blocked": false, "is_tmp": false, "name_id": 0, "text": "会不会社死hhhh", "timestamp": 1659283402}, {"author_title": "", "blocked": false, "blocked_count": null, "can_del": false, "cid": 322050, "create_time": 1659283742, "is_blocked": false, "is_tmp": false, "name_id": 1, "text": "不会，这是善意取得", "timestamp": 1659283742}], "create_time": 1659283394, "cw": null, "hot_score": null, "is_blocked": false, "is_reported": null, "is_tmp": false, "last_comment_time": 1659283742, "likenum": 2, "n_attentions": 2, "n_comments": 2, "pid": 91447, "poll": null, "reply": 2, "text": "如果被身边的人发现我会捡别人不要的收纳盒和衣架……", "timestamp": 1659283394}}