{"code": 0, "data": {"allow_search": true, "attention": false, "author_title": null, "blocked": false, "blocked_count": null, "can_del": false, "comments": [{"author_title": "", "blocked": false, "blocked_count": null, "can_del": false, "cid": 324832, "create_time": 1659451759, "is_blocked": false, "is_tmp": false, "name_id": 1, "text": "怎么挣钱 求教", "timestamp": 1659451759}, {"author_title": "", "blocked": false, "blocked_count": null, "can_del": false, "cid": 324834, "create_time": 1659451830, "is_blocked": false, "is_tmp": false, "name_id": 2, "text": "我也是，这几天放下工作，出来玩了五天", "timestamp": 1659451830}], "create_time": 1659451709, "cw": null, "hot_score": null, "is_blocked": false, "is_reported": null, "is_tmp": false, "last_comment_time": 1659451830, "likenum": 5, "n_attentions": 5, "n_comments": 2, "pid": 92535, "poll": null, "reply": 2, "text": "暑假在家里一个多月，每天各种线上工作挣钱，这样的生活是不是。。。不那么好\n", "timestamp": 1659451709}}